{
  "collider": {
    "number": 3,
    "size": [
      0.4,
      0.4,
      0.9
    ],
    "center": [
      0.0,
      0.0,
      -0.35
    ]
  },
  "hit_particle": "epicfight:hit_blade",
  "hit_sound": "refm:entity.weapon.rapier_hit",
  "livingmotion_modifier": {
    "two_hand": {
      "idle": "wom:biped/living/ruine_idle",
      "run": "refm:biped/living/run_rapier",
      "block": "refm:biped/skill/guard_rapier",
      "walk": "refm:biped/living/walk_rapier"
    }
  },
  "swing_sound": "refm:entity.weapon.rapier_stab",
 "styles": {
    "default": "two_hand",
    "cases": [
      {
        "style": "two_hand",
        "conditions": [
          {
            "predicate": "epicfight:offhand_item_category",
            "category": "rapier"
          }
        ]
      },
  {
        "style": "mount",
        "conditions": [
          {
            "predicate": "epicfight:offhand_item_category",
            "category": "rapier"
          }
        ]
      }
    ]
  },
  "combos": {
"mount": [
      "wom:biped/combat/agony_auto_1",
      "epicacg:biped/sao_rapier/sao_rapier_auto1"
    ],
    "two_hand": [
      "wom:biped/combat/agony_auto_1",
      "refm:biped/combat/rapier_auto1",
      "refm:biped/combat/rapier_auto3",
      "refm:biped/combat/rapier_dash",
      "refm:biped/combat/rapier_airslash"
    ]
  },
  "category": "rapier",
  "innate_skills": {
    "two_hand": "refm:deadlybackflip"
  },
  "usable_in_offhand": false
}